altmol/__init__.py
altmol/chem.py
altmol/plot.py
altmol-0.2.2.dist-info/LICENSE
altmol-0.2.2.dist-info/METADATA
altmol-0.2.2.dist-info/WHEEL
altmol-0.2.2.dist-info/RECORD
