Metadata-Version: 2.1
Name: altmol
Version: 0.2.2
Summary: 
Author: Tagir Akhmetshin
Author-email: tagirshin@gmail.com
Requires-Python: >=3.9,<3.13
Classifier: Programming Language :: Python :: 3
Classifier: Programming Language :: Python :: 3.9
Classifier: Programming Language :: Python :: 3.10
Classifier: Programming Language :: Python :: 3.11
Classifier: Programming Language :: Python :: 3.12
Requires-Dist: altair (>=5,<6)
Requires-Dist: numpy (>=1.25)
Requires-Dist: pandas (>=2.1)
Requires-Dist: rdkit (>=2023.9.6,<2024.0.0)
